sourcegraph/__init__.py
sourcegraph/source_graph.py
sourcegraph/utils.py
sourcegraph-0.0.7.dist-info/METADATA
sourcegraph-0.0.7.dist-info/WHEEL
sourcegraph-0.0.7.dist-info/licenses/LICENSE
sourcegraph-0.0.7.dist-info/RECORD
