Metadata-Version: 2.3
Name: sourcegraph
Version: 0.0.7
Summary: Convert GitHub Repo Into Graph
Project-URL: Code, https://github.com/Ransaka/sourcegraph
Project-URL: Docs, https://github.com/Ransaka/sourcegraph
Author-email: Ransaka <ransaka.ravihara@gmail.com>
License: MIT License
License-File: LICENSE
Keywords: NetworkX,Python
Classifier: License :: OSI Approved :: MIT License
Classifier: Programming Language :: Python :: 3.9
Classifier: Programming Language :: Python :: 3.10
Classifier: Programming Language :: Python :: 3.11
Classifier: Topic :: Scientific/Engineering :: Artificial Intelligence
Requires-Python: <=3.12,>=3.9.7
Requires-Dist: gitpython~=3.1.43
Requires-Dist: matplotlib~=3.8.4
Requires-Dist: networkx~=3.2.1
